pygitver/__init__.py
pygitver/changelogs_mngr.py
pygitver/git.py
pygitver/pygitver.py
pygitver/scripts/install.sh
pygitver/scripts/git/hooks/commit-msg
pygitver/templates/changelog-common.tmpl
pygitver/templates/changelog.tmpl
pygitver-0.2.3.dist-info/METADATA
pygitver-0.2.3.dist-info/WHEEL
pygitver-0.2.3.dist-info/entry_points.txt
pygitver-0.2.3.dist-info/licenses/LICENSE
pygitver-0.2.3.dist-info/RECORD
