Metadata-Version: 2.3
Name: pygitver
Version: 0.2.3
Summary: Manages Git Tag versions and generates ChangeLog
Project-URL: Homepage, https://github.com/panpuchkov/pygitver
Author-email: Yurii Puchkov <panpuchkov@gmail.com>
License: GPL-3.0-or-later
Keywords: changelog,changelogs,conventional commit,git tag,semver,version,versions
Classifier: Development Status :: 5 - Production/Stable
Classifier: Environment :: Console
Classifier: Natural Language :: English
Classifier: Operating System :: OS Independent
Classifier: Programming Language :: Python :: 3
Requires-Python: >=3.8
Requires-Dist: jinja2==3.1.2
